MANIFEST.in
README.md
requirements.txt
setup.cfg
setup.py
etc/Model2WADL.cfg
etc/Physical2Virtual.cfg
etc/logging.conf
xWoTModelTranslator.egg-info/PKG-INFO
xWoTModelTranslator.egg-info/SOURCES.txt
xWoTModelTranslator.egg-info/dependency_links.txt
xWoTModelTranslator.egg-info/entry_points.txt
xWoTModelTranslator.egg-info/requires.txt
xWoTModelTranslator.egg-info/top_level.txt
xwot1/__init__.py
xwot1/cmd.py
xwot1/model2Python.py
xwot1/model2WADL.py
xwot1/physical2virtualEntities.py
xwot1/NM_REST-Server-Skeleton/README.md
xwot1/NM_REST-Server-Skeleton/WebSocketSupport.py
xwot1/NM_REST-Server-Skeleton/ZeroconfigService.py
xwot1/NM_REST-Server-Skeleton/render_DELETE.txt
xwot1/NM_REST-Server-Skeleton/render_GET.txt
xwot1/NM_REST-Server-Skeleton/render_POST.txt
xwot1/NM_REST-Server-Skeleton/render_PUT.txt
xwot1/NM_REST-Server-Skeleton/requirements.txt
xwot1/NM_REST-Server-Skeleton/resourceAPI_skeleton.py
xwot1/NM_REST-Server-Skeleton/rest-documentation.html
xwot1/NM_REST-Server-Skeleton/rest-server.py
xwot1/NM_REST-Server-Skeleton/setup.bat
xwot1/NM_REST-Server-Skeleton/setup.sh
xwot1/NM_REST-Server-Skeleton/virtualenv.py
xwot1/NM_REST-Server-Skeleton/templates/__init__.py
xwot1/NM_REST-Server-Skeleton/templates/index.html
xwot1/NM_REST-Server-Skeleton/templates/robots.txt
xwot1/NM_REST-Server-Skeleton/templates/tpl_temperature.py
xwot1/NM_REST-Server-Skeleton/templates/tpl_temperature.xml
xwot1/NM_REST-Server-Skeleton/templates/css/application.css
xwot1/NM_REST-Server-Skeleton/templates/css/foundation-icons.css
xwot1/NM_REST-Server-Skeleton/templates/css/foundation.css
xwot1/NM_REST-Server-Skeleton/templates/css/foundation.min.css
xwot1/NM_REST-Server-Skeleton/templates/css/foundation_and_overrides.css
xwot1/NM_REST-Server-Skeleton/templates/css/normalize.css
xwot1/NM_REST-Server-Skeleton/templates/img/.gitkeep
xwot1/NM_REST-Server-Skeleton/templates/js/application.js
xwot1/NM_REST-Server-Skeleton/templates/js/foundation.js
xwot1/NM_REST-Server-Skeleton/templates/js/foundation.min.js
xwot1/NM_REST-Server-Skeleton/templates/js/jquery.js
xwot1/NM_REST-Server-Skeleton/templates/js/jquery_ujs.js
xwot1/NM_REST-Server-Skeleton/templates/js/modernizr.js
xwot1/NM_REST-Server-Skeleton/templates/js/foundation/foundation.abide.js
